atomictoolkit/__init__.py
atomictoolkit/io_handlers.py
atomictoolkit/mcp_server.py
atomictoolkit/optimizers.py
atomictoolkit/structure_operations.py
atomictoolkit_mcp-0.1.1.dist-info/licenses/LICENSE
atomictoolkit_mcp-0.1.1.dist-info/METADATA
atomictoolkit_mcp-0.1.1.dist-info/WHEEL
atomictoolkit_mcp-0.1.1.dist-info/entry_points.txt
atomictoolkit_mcp-0.1.1.dist-info/top_level.txt
atomictoolkit_mcp-0.1.1.dist-info/RECORD
