Metadata-Version: 2.4
Name: atomictoolkit-mcp
Version: 0.1.1
Summary: MCP server for ASE and more.
Requires-Python: >=3.13
License-File: LICENSE
Requires-Dist: ase>=3.24.0
Requires-Dist: fastmcp>=0.4.1
Requires-Dist: mcp[cli]>=1.4.1
Requires-Dist: orb-models>=0.4.2
Requires-Dist: pymatgen>=2025.3.10
Requires-Dist: pynanoflann>=0.10.0
Dynamic: license-file
